Metadata-Version: 2.1
Name: viniciusrcs_image_processing
Version: 0.0.1
Summary: Image Processing Package using Skimage
Author: Vinicius
Requires-Python: >=3.6
Requires-Dist: matplotlib
Requires-Dist: numpy
Requires-Dist: scikit-image >=0.16.1
